{
  "base_price": 2995,
  "beamstation_catalog_url": "https://beamstation.com/datasets",
  "beamstation_origin": "https://beamstation.com",
  "category_group_name": "Restaurants",
  "config_category": "email",
  "config_description": "--Reach Independent Inboxes--\n\nWeekly verified, high-deliverability emails.\n\nOnly for established, independent restaurants (or micro-chains) \u2013 large chain enterprises excluded.\n\nWeekly email verification and detailed analysis via our proprietary infrastructure.\n\nBusiness activity validated by an \"Active Heartbeat\" signal.",
  "config_name": "Restaurant Verified Email Access in Colorado, US",
  "export_job_id": "bdeebd8d-eba2-44f9-86a4-e72542533e57",
  "github_org": "Beamstation-Datasets",
  "id_short": 602591,
  "location_name": "Colorado",
  "location_type": "state",
  "repo_name": "restaurant-verified-email-access-in-colorado-us-sample-602591",
  "sample_b2_path": "b2-export:BeamStation-ExportFiles/602591/beamstation_602591_restaurants-us-co_SAMPLE_DIST.csv",
  "sample_pct": 9.99,
  "sample_records": 257,
  "sample_sha256": "30c93dbe1e8167653956982827575be8b068d6a4c0090c8985f32b9294610612",
  "sample_size_bytes": 1049520,
  "total_records": 2573,
  "updated_at": "2026-04-22T09:19:23.293773+00:00"
}